alembic_postgresql_enum/__init__.py
alembic_postgresql_enum/add_create_type_false.py
alembic_postgresql_enum/add_postgres_using_to_text.py
alembic_postgresql_enum/compare_dispatch.py
alembic_postgresql_enum/configuration.py
alembic_postgresql_enum/connection.py
alembic_postgresql_enum/detection_of_changes/__init__.py
alembic_postgresql_enum/detection_of_changes/enum_alteration.py
alembic_postgresql_enum/detection_of_changes/enum_creation.py
alembic_postgresql_enum/detection_of_changes/enum_deletion.py
alembic_postgresql_enum/get_enum_data/__init__.py
alembic_postgresql_enum/get_enum_data/declared_enums.py
alembic_postgresql_enum/get_enum_data/defined_enums.py
alembic_postgresql_enum/get_enum_data/get_default_from_alembic_ops.py
alembic_postgresql_enum/get_enum_data/types.py
alembic_postgresql_enum/operations/__init__.py
alembic_postgresql_enum/operations/create_enum.py
alembic_postgresql_enum/operations/drop_enum.py
alembic_postgresql_enum/operations/enum_lifecycle_base.py
alembic_postgresql_enum/operations/sync_enum_values.py
alembic_postgresql_enum/py.typed
alembic_postgresql_enum/sql_commands/column_default.py
alembic_postgresql_enum/sql_commands/comparison_operators.py
alembic_postgresql_enum/sql_commands/enum_type.py
alembic_postgresql_enum-1.6.1.dist-info/LICENSE
alembic_postgresql_enum-1.6.1.dist-info/METADATA
alembic_postgresql_enum-1.6.1.dist-info/WHEEL
alembic_postgresql_enum-1.6.1.dist-info/RECORD
