Metadata-Version: 2.3
Name: alembic-postgresql-enum
Version: 1.6.1
Summary: Alembic autogenerate support for creation, alteration and deletion of enums
License: MIT
Author: RustyGuard
Requires-Python: >=3.7,<4.0
Classifier: Development Status :: 4 - Beta
Classifier: Intended Audience :: Developers
Classifier: License :: OSI Approved :: MIT License
Classifier: Programming Language :: Python :: 3
Classifier: Programming Language :: Python :: 3.7
Classifier: Programming Language :: Python :: 3.8
Classifier: Programming Language :: Python :: 3.9
Classifier: Programming Language :: Python :: 3.10
Classifier: Programming Language :: Python :: 3.11
Classifier: Programming Language :: Python :: 3.12
Classifier: Programming Language :: Python :: 3.13
Requires-Dist: SQLAlchemy (>=1.4)
Requires-Dist: alembic (>=1.7)
Project-URL: Source code, https://github.com/RustyGuard/alembic-postgresql-enum
